brainfork/__init__.py
brainfork/models.py
brainfork/py.typed
brainfork/router.py
brainfork-0.1.2.dist-info/licenses/LICENSE
brainfork-0.1.2.dist-info/METADATA
brainfork-0.1.2.dist-info/WHEEL
brainfork-0.1.2.dist-info/top_level.txt
brainfork-0.1.2.dist-info/RECORD
