Metadata-Version: 2.4
Name: brainfork
Version: 0.1.2
Summary: An intelligent AI model router for Azure OpenAI that automatically selects the best model for your specific use case
Home-page: https://github.com/pfekrati/brainfork
Author: Pooyan
Author-email: Pooyan Fekrati <p.fekrati@hotmail.com>
Maintainer-email: Pooyan Fekrati <p.fekrati@hotmail.com>
License: MIT
Project-URL: Homepage, https://github.com/pfekrati/brainfork
Project-URL: Repository, https://github.com/pfekrati/brainfork
Project-URL: Issues, https://github.com/pfekrati/brainfork/issues
Project-URL: Documentation, https://github.com/pfekrati/brainfork#readme
Keywords: azure,openai,ai,model,router,llm,gpt
Classifier: Development Status :: 3 - Alpha
Classifier: Intended Audience :: Developers
Classifier: License :: OSI Approved :: MIT License
Classifier: Operating System :: OS Independent
Classifier: Programming Language :: Python :: 3
Classifier: Programming Language :: Python :: 3.8
Classifier: Programming Language :: Python :: 3.9
Classifier: Programming Language :: Python :: 3.10
Classifier: Programming Language :: Python :: 3.11
Classifier: Programming Language :: Python :: 3.12
Classifier: Topic :: Software Development :: Libraries :: Python Modules
Classifier: Topic :: Scientific/Engineering :: Artificial Intelligence
Requires-Python: >=3.8
License-File: LICENSE
Requires-Dist: openai>=1.0.0
Requires-Dist: azure-identity>=1.12.0
Requires-Dist: pydantic>=2.0.0
Requires-Dist: aiohttp>=3.8.0
Dynamic: author
Dynamic: home-page
Dynamic: license-file
Dynamic: requires-python
